[{"__type__":"cc.SpriteFrame","content":{"name":"ropeDog1","texture":"6fHS5JTOdBbY0qBoXIYZnP","rect":[0,0,204,628],"offset":[0,12.5],"originalSize":[204,653],"capInsets":[0,0,0,0]}},{"__type__":"cc.SpriteFrame","content":{"name":"ropeMouse1","texture":"ab+Tm6S85GrKxRCGTKwCun","rect":[0,0,204,649],"offset":[0,2],"originalSize":[204,653],"capInsets":[0,0,0,0]}},{"__type__":"cc.SpriteFrame","content":{"name":"button_off","texture":"bdGyfsNIxJPqVpBc6UfRIq","rect":[0,0,173,129],"offset":[0,0],"originalSize":[173,129],"capInsets":[0,0,0,0]}},{"__type__":"cc.SpriteFrame","content":{"name":"bear1_1","texture":"cc3oRmC/RJrrHzXVxDvEAo","rect":[28,44,212,219],"offset":[-46,-3.5],"originalSize":[360,300],"capInsets":[0,0,0,0]}},{"__type__":"cc.SpriteFrame","content":{"name":"cow1_2","texture":"4dJQV56TdHj7RHvlKvA78d","rect":[6,9,354,291],"offset":[3,-4.5],"originalSize":[360,300],"capInsets":[0,0,0,0]}},{"__type__":"cc.SpriteFrame","content":{"name":"dog1_2","texture":"dd5CVX5+JFka6vTIEfJHto","rect":[72,19,214,265],"offset":[-1,-1.5],"originalSize":[360,300],"capInsets":[0,0,0,0]}},[{"__type__":"cc.SceneAsset","_name":"game_scene","scene":{"__id__":1},"asyncLoadAssets":null},{"__type__":"cc.Scene","_name":"New Node","_children":[{"__id__":2}],"_active":false,"_anchorPoint":{"__type__":"cc.Vec2"},"autoReleaseAssets":false},{"__type__":"cc.Node","_name":"Canvas","_parent":{"__id__":1},"_children":[{"__id__":3},{"__id__":4},{"__id__":5},{"__id__":8},{"__id__":9},{"__id__":11},{"__id__":12}],"_level":1,"_components":[{"__type__":"cc.Canvas","node":{"__id__":2},"_designResolution":{"__type__":"cc.Size","width":640,"height":960},"_fitWidth":true},{"__type__":"a05a2eOTUhNwbpcFbFTjIVc","node":{"__id__":2},"claw":{"__id__":8},"score":{"__id__":14},"claw_pics":[{"__uuid__":"27EJI9JRVIMpOFECxanUBi"},{"__uuid__":"a0ELUYWbNBFYMycG7MjJt2"},{"__uuid__":"2eA+MG+WxI4KL+izjO6SX3"},{"__uuid__":"2cXhsNFqVEOYGejvBw3Bjt"},{"__uuid__":"d0+a5pNRNPMJ9/ZNpsJVCw"},{"__uuid__":"ed0bd1Z/NKSKY7lOgvDYng"},{"__uuid__":"010vBPYShDspt3wfnUCs8f"},{"__uuid__":"07GMIPy8REiYCwEENSOwrb"},{"__uuid__":"c3ZzvXyr1OKaZfl34ResLw"}],"toy_node":{"__id__":5},"toy_prefab":{"__uuid__":"70pAarcFJA4L9+TVzBv9es"}}],"_contentSize":{"__type__":"cc.Size","width":640,"height":960},"_position":{"__type__":"cc.Vec3","x":320,"y":480},"_id":"6a/bCW0VJAvqn5GVoVRyc/"},{"__type__":"cc.Node","_name":"Main Camera","_parent":{"__id__":2},"_level":1,"_components":[{"__type__":"cc.Camera","node":{"__id__":3},"_clearFlags":7,"_depth":-1}],"_position":{"__type__":"cc.Vec3","z":256.34351952019387}},{"__type__":"cc.Node","_name":"bg","_parent":{"__id__":2},"_level":1,"_components":[{"__type__":"cc.Sprite","node":{"__id__":4},"_materials":[{"__uuid__":"ecpdLyjvZBwrvm+cedCcQy"}],"_spriteFrame":{"__uuid__":"cazy8P8f5D05yOuSX79WRQ"},"_sizeMode":0}],"_contentSize":{"__type__":"cc.Size","width":640,"height":960}},{"__type__":"cc.Node","_name":"toyNode","_parent":{"__id__":2},"_children":[{"__id__":6}],"_level":1},{"__type__":"cc.Node","_name":"toy","_parent":{"__id__":5},"_children":[{"__id__":7}],"_level":2,"_components":[{"__type__":"e89c4YAfgRDda9s07QjucvT","node":{"__id__":6},"cow_skin_set":[{"__type__":"cow_skin","cow_anim":[{"__uuid__":"43Caumz7hJcICSWJejvjLm"},{"__uuid__":"18GPoPsV5DAL+7JhsemVkf"},{"__uuid__":"5aMSZpAotEfYrdpxJHjhlv"}]},{"__type__":"cow_skin","cow_anim":[{"__uuid__":"5ecKW11PJAWYc7AgCgS0tJ"},{"__uuid__":"495F4q7L5CDay+tRYYETqG"},{"__uuid__":"45m190NVFH/5ErEAnn9Bxo"}]},{"__type__":"cow_skin","cow_anim":[{"__uuid__":"deQMznjJxCqY+6XyGHzpra"},{"__uuid__":"7fW4o63IVNsbW4hbaCLhvK"},{"__uuid__":"89nPqvFdNDY6MWr5HW/+nI"}]}]}],"_prefab":{"__type__":"cc.PrefabInfo","root":{"__id__":6},"asset":{"__uuid__":"70pAarcFJA4L9+TVzBv9es"},"fileId":"74MbIlV+RJNajcKnr6iFAr"},"_position":{"__type__":"cc.Vec3","x":156,"y":-80}},{"__type__":"cc.Node","_name":"anim","_parent":{"__id__":6},"_level":3,"_components":[{"__type__":"cc.Sprite","node":{"__id__":7},"_materials":[{"__uuid__":"ecpdLyjvZBwrvm+cedCcQy"}],"_spriteFrame":{"__uuid__":"43Caumz7hJcICSWJejvjLm"}}],"_prefab":{"__type__":"cc.PrefabInfo","root":{"__id__":6},"asset":{"__uuid__":"70pAarcFJA4L9+TVzBv9es"},"fileId":"3e0Zh2ciBKP46dzXevSA9g"},"_contentSize":{"__type__":"cc.Size","width":354,"height":293}},{"__type__":"cc.Node","_name":"claw","_parent":{"__id__":2},"_level":2,"_components":[{"__type__":"cc.Sprite","node":{"__id__":8},"_materials":[{"__uuid__":"ecpdLyjvZBwrvm+cedCcQy"}],"_spriteFrame":{"__uuid__":"a0ELUYWbNBFYMycG7MjJt2"}}],"_contentSize":{"__type__":"cc.Size","width":204,"height":653},"_position":{"__type__":"cc.Vec3","y":164}},{"__type__":"cc.Node","_name":"clow","_parent":{"__id__":2},"_children":[{"__id__":10}],"_level":2,"_contentSize":{"__type__":"cc.Size","width":100,"height":100},"_position":{"__type__":"cc.Vec3","y":510}},{"__type__":"cc.Node","_name":"clow_top","_parent":{"__id__":9},"_level":3,"_components":[{"__type__":"cc.Sprite","node":{"__id__":10},"_materials":[{"__uuid__":"ecpdLyjvZBwrvm+cedCcQy"}],"_spriteFrame":{"__uuid__":"97rvlY1rtAiIn0iLB8AM14"},"_sizeMode":0}],"_color":{"__type__":"cc.Color","r":255,"g":106,"b":51},"_contentSize":{"__type__":"cc.Size","width":100,"height":100}},{"__type__":"cc.Node","_name":"btn","_parent":{"__id__":2},"_level":1,"_components":[{"__type__":"cc.Sprite","node":{"__id__":11},"_materials":[{"__uuid__":"ecpdLyjvZBwrvm+cedCcQy"}],"_spriteFrame":{"__uuid__":"0eofATVtJBrY0heI1DQJzO"},"_type":1,"_sizeMode":2},{"__type__":"cc.Button","node":{"__id__":11},"clickEvents":[{"__type__":"cc.ClickEvent","target":{"__id__":2},"_componentId":"a05a2eOTUhNwbpcFbFTjIVc","handler":"on_btn_click"}],"_N$transition":2,"transition":2,"_N$normalSprite":{"__uuid__":"0eofATVtJBrY0heI1DQJzO"},"_N$pressedSprite":{"__uuid__":"6fORrCcXdMBY9NFeLk3OJ9"},"pressedSprite":{"__uuid__":"6fORrCcXdMBY9NFeLk3OJ9"},"_N$hoverSprite":{"__uuid__":"0eofATVtJBrY0heI1DQJzO"},"hoverSprite":{"__uuid__":"0eofATVtJBrY0heI1DQJzO"},"_N$disabledSprite":{"__uuid__":"6fORrCcXdMBY9NFeLk3OJ9"}}],"_contentSize":{"__type__":"cc.Size","width":173,"height":129},"_position":{"__type__":"cc.Vec3","y":-441}},{"__type__":"cc.Node","_name":"count","_parent":{"__id__":2},"_children":[{"__id__":13}],"_level":2,"_components":[{"__type__":"cc.Sprite","node":{"__id__":12},"_materials":[{"__uuid__":"ecpdLyjvZBwrvm+cedCcQy"}],"_spriteFrame":{"__uuid__":"fapMSPbipCCq8tCXvsLMZq"}}],"_contentSize":{"__type__":"cc.Size","width":185,"height":94},"_position":{"__type__":"cc.Vec3","x":-198.75,"y":401.25}},{"__type__":"cc.Node","_name":"score","_parent":{"__id__":12},"_level":3,"_components":[{"__id__":14}],"_contentSize":{"__type__":"cc.Size","width":66.74,"height":50.4},"_position":{"__type__":"cc.Vec3","x":33.171,"y":2.764}},{"__type__":"cc.Label","node":{"__id__":13},"_materials":[{"__uuid__":"ecpdLyjvZBwrvm+cedCcQy"}],"_useOriginalSize":false,"_string":"100","_N$string":"100","_N$horizontalAlign":1,"_N$verticalAlign":1}],{"__type__":"cc.SpriteFrame","content":{"name":"claw1","texture":"52WDQmwfFKUpnUNK6AObAb","rect":[0,0,204,561],"offset":[0,46],"originalSize":[204,653],"capInsets":[0,0,0,0]}},{"__type__":"cc.SpriteFrame","content":{"name":"ropeCow3","texture":"830fzKfbFEV5k8EjOPPVSy","rect":[0,0,204,653],"offset":[0,0],"originalSize":[204,653],"capInsets":[0,0,0,0]}},{"__type__":"cc.SpriteFrame","content":{"name":"ropeCow2","texture":"22MGwthM9EV5IZm7UCCCAO","rect":[0,0,204,653],"offset":[0,0],"originalSize":[204,653],"capInsets":[0,0,0,0]}},{"__type__":"cc.SpriteFrame","content":{"name":"dog1_3","texture":"21Jlua7OxFyKDMj9Br5BNY","rect":[74,11,194,271],"offset":[-9,3.5],"originalSize":[360,300],"capInsets":[0,0,0,0]}},{"__type__":"cc.SpriteFrame","content":{"name":"cow1_1","texture":"7dm1RAkBRB+40rEJ4yYjDx","rect":[3,7,354,293],"offset":[0,-3.5],"originalSize":[360,300],"capInsets":[0,0,0,0]}},{"__type__":"cc.SpriteFrame","content":{"name":"cow2_3","texture":"29m93OMz1DqYDLRbWB00BC","rect":[5,18,354,282],"offset":[2,-9],"originalSize":[360,300],"capInsets":[0,0,0,0]}},{"__type__":"cc.SpriteFrame","content":{"name":"cow2_2","texture":"1clkUZEHFF1aK0CeWsWoyr","rect":[7,16,353,279],"offset":[3.5,-5.5],"originalSize":[360,300],"capInsets":[0,0,0,0]}},{"__type__":"cc.SpriteFrame","content":{"name":"cat1_1","texture":"219wiviTpBMYdiM22AjeFP","rect":[74,19,134,256],"offset":[-39,3],"originalSize":[360,300],"capInsets":[0,0,0,0]}},{"__type__":"cc.SpriteFrame","content":{"name":"cow1_3","texture":"61GOFd2PhFK6e/xGleqbmb","rect":[1,16,359,279],"offset":[0.5,-5.5],"originalSize":[360,300],"capInsets":[0,0,0,0]}},{"__type__":"cc.SpriteFrame","content":{"name":"cow2_1","texture":"ac2YXr4o5Lh5fWbaj+hFJe","rect":[4,15,352,279],"offset":[0,-4.5],"originalSize":[360,300],"capInsets":[0,0,0,0]}},{"__type__":"cc.SpriteFrame","content":{"name":"button_on","texture":"623dkDtKlDwr2tK5ZRJCyl","rect":[0,9,173,120],"offset":[0,-4.5],"originalSize":[173,129],"capInsets":[0,0,0,0]}},[{"__type__":"cc.Prefab","_name":"toy","data":{"__id__":1}},{"__type__":"cc.Node","_name":"toy","_children":[{"__id__":2}],"_level":1,"_components":[{"__type__":"e89c4YAfgRDda9s07QjucvT","node":{"__id__":1},"cow_skin_set":[{"__type__":"cow_skin","cow_anim":[{"__uuid__":"43Caumz7hJcICSWJejvjLm"},{"__uuid__":"18GPoPsV5DAL+7JhsemVkf"},{"__uuid__":"5aMSZpAotEfYrdpxJHjhlv"}]},{"__type__":"cow_skin","cow_anim":[{"__uuid__":"5ecKW11PJAWYc7AgCgS0tJ"},{"__uuid__":"495F4q7L5CDay+tRYYETqG"},{"__uuid__":"45m190NVFH/5ErEAnn9Bxo"}]},{"__type__":"cow_skin","cow_anim":[{"__uuid__":"deQMznjJxCqY+6XyGHzpra"},{"__uuid__":"7fW4o63IVNsbW4hbaCLhvK"},{"__uuid__":"89nPqvFdNDY6MWr5HW/+nI"}]},{"__type__":"cow_skin","cow_anim":[{"__uuid__":"0fntUAHsxAFIk5KNwXnFu9"},{"__uuid__":"8d8N5nSzZB14LxMWCiFgAB"},{"__uuid__":"deguxC2V1Gyp1Ar4EYgl6d"}]},{"__type__":"cow_skin","cow_anim":[{"__uuid__":"4eIjeUufZFm40LRRTyE/+n"},{"__uuid__":"a7+qhLMtlGy4Q0jVygqAq0"},{"__uuid__":"fdwKy4UyRBuqngmph4WUzo"}]},{"__type__":"cow_skin","cow_anim":[{"__uuid__":"e5WIilpatH9555W0Kpi+v2"},{"__uuid__":"19zsg+fSFAzq6BlyF0TeON"},{"__uuid__":"31xH10YqlB2bydiwKGkR7v"}]},{"__type__":"cow_skin","cow_anim":[{"__uuid__":"8dDYNk8rNIooY3D2DP6ckj"},{"__uuid__":"faTWwAdzJHcby044zGatP/"},{"__uuid__":"8eqkA0xt5Boax+n2KZtFFi"}]},{"__type__":"cow_skin","cow_anim":[{"__uuid__":"99g1OhZUFFubjrIaz1NO5K"},{"__uuid__":"fal6sgYd1EjZvADLvgMvF8"},{"__uuid__":"aaoFYFB9ZC+IWN+RsYTwZ2"}]}]}],"_prefab":{"__type__":"cc.PrefabInfo","root":{"__id__":1},"asset":{"__uuid__":"70pAarcFJA4L9+TVzBv9es"},"fileId":"74MbIlV+RJNajcKnr6iFAr"}},{"__type__":"cc.Node","_name":"anim","_parent":{"__id__":1},"_level":3,"_components":[{"__type__":"cc.Sprite","node":{"__id__":2},"_materials":[{"__uuid__":"ecpdLyjvZBwrvm+cedCcQy"}],"_spriteFrame":{"__uuid__":"43Caumz7hJcICSWJejvjLm"}}],"_prefab":{"__type__":"cc.PrefabInfo","root":{"__id__":1},"asset":{"__uuid__":"70pAarcFJA4L9+TVzBv9es"},"fileId":"3e0Zh2ciBKP46dzXevSA9g"},"_contentSize":{"__type__":"cc.Size","width":354,"height":293}}],{"__type__":"cc.SpriteFrame","content":{"name":"cow3_2","texture":"c1GGPdz31JbIKmq/NfiVvQ","rect":[7,16,353,280],"offset":[3.5,-6],"originalSize":[360,300],"capInsets":[0,0,0,0]}},{"__type__":"cc.SpriteFrame","content":{"name":"cow3_3","texture":"d44F4dLz5HZLlcmia9/aSN","rect":[8,19,352,280],"offset":[4,-9],"originalSize":[360,300],"capInsets":[0,0,0,0]}},{"__type__":"cc.SpriteFrame","content":{"name":"mouse1_1","texture":"0eE3Y2L/BDrJjnXNRo/EDE","rect":[3,0,269,295],"offset":[-42.5,2.5],"originalSize":[360,300],"capInsets":[0,0,0,0]}},{"__type__":"cc.SpriteFrame","content":{"name":"bear1_2","texture":"69kCQnCnFEk6jqFuKKuiFy","rect":[44,0,180,263],"offset":[-46,18.5],"originalSize":[360,300],"capInsets":[0,0,0,0]}},{"__type__":"cc.SpriteFrame","content":{"name":"mouse1_3","texture":"a9n86+fn1ADLjPWsMPLIRH","rect":[36,7,253,293],"offset":[-17.5,-3.5],"originalSize":[360,300],"capInsets":[0,0,0,0]}},{"__type__":"cc.SpriteFrame","content":{"name":"circle","texture":"50r/R9p2FGyKzYc46xfYZ3","rect":[0,0,500,500],"offset":[0,0],"originalSize":[500,500],"capInsets":[0,0,0,0]}},{"__type__":"cc.SpriteFrame","content":{"name":"rabbit1_1","texture":"44O9jT6uBJr4mYQIC1eKic","rect":[76,23,150,241],"offset":[-29,6.5],"originalSize":[360,300],"capInsets":[0,0,0,0]}},{"__type__":"cc.SpriteFrame","content":{"name":"ropeCow1","texture":"31M1iQT4BED5HyZR5cVlbR","rect":[0,0,204,653],"offset":[0,0],"originalSize":[204,653],"capInsets":[0,0,0,0]}},{"__type__":"cc.SpriteFrame","content":{"name":"cat1_2","texture":"b5X9Pn2zJOR5HjAkbQ+jY+","rect":[41,93,182,108],"offset":[-48,3],"originalSize":[360,300],"capInsets":[0,0,0,0]}},{"__type__":"cc.SpriteFrame","content":{"name":"rabbit1_3","texture":"225p6wOpxAmq5P4jNwvLwz","rect":[48,7,186,257],"offset":[-39,14.5],"originalSize":[360,300],"capInsets":[0,0,0,0]}},{"__type__":"cc.SpriteFrame","content":{"name":"ropeRabbit1","texture":"4efEqa3UNIHJSOnbRY6z17","rect":[0,0,204,637],"offset":[0,8],"originalSize":[204,653],"capInsets":[0,0,0,0]}},{"__type__":"cc.SpriteFrame","content":{"name":"bg","texture":"abqJ4zoPpBB6QwRFC7cUP5","rect":[0,0,640,960],"offset":[0,0],"originalSize":[640,960],"capInsets":[0,0,0,0]}},{"__type__":"cc.SpriteFrame","content":{"name":"ropeBear1","texture":"cfn7VIHC5C1qF3wP2A0+kF","rect":[0,0,204,586],"offset":[0,33.5],"originalSize":[204,653],"capInsets":[0,0,0,0]}},{"__type__":"cc.SpriteFrame","content":{"name":"cow3_1","texture":"6fvEdkhzxFdqpQd760AU5R","rect":[8,16,352,280],"offset":[4,-6],"originalSize":[360,300],"capInsets":[0,0,0,0]}},{"__type__":"cc.SpriteFrame","content":{"name":"bear1_3","texture":"84prZCrcJCEq/tn9JsZ1Cg","rect":[0,44,239,209],"offset":[-60.5,1.5],"originalSize":[360,300],"capInsets":[0,0,0,0]}},{"__type__":"cc.SpriteFrame","content":{"name":"dog1_1","texture":"0baaMwW51A8qKAZ+fMAgrl","rect":[74,11,221,272],"offset":[4.5,3],"originalSize":[360,300],"capInsets":[0,0,0,0]}},{"__type__":"cc.SpriteFrame","content":{"name":"ropeCat1","texture":"99o4Bgk/lOUYUxsl5EZWeD","rect":[0,0,204,653],"offset":[0,0],"originalSize":[204,653],"capInsets":[0,0,0,0]}},{"__type__":"cc.SpriteFrame","content":{"name":"mouse1_2","texture":"d1jpu3BFNLY7fLmfNPETGp","rect":[21,7,259,287],"offset":[-29.5,-0.5],"originalSize":[360,300],"capInsets":[0,0,0,0]}},{"__type__":"cc.SpriteFrame","content":{"name":"rabbit1_2","texture":"85OSFOfypHC5O2D7T2gKrC","rect":[76,20,158,244],"offset":[-25,8],"originalSize":[360,300],"capInsets":[0,0,0,0]}},{"__type__":"cc.SpriteFrame","content":{"name":"count","texture":"12uDB5HEtHXI+qZ1RyjQCB","rect":[0,0,185,94],"offset":[0,0],"originalSize":[185,94],"capInsets":[0,0,0,0]}},{"__type__":"cc.SpriteFrame","content":{"name":"cat1_3","texture":"670OW+B9JJNqdYg+WtRUuL","rect":[76,58,135,194],"offset":[-36.5,-5],"originalSize":[360,300],"capInsets":[0,0,0,0]}}]